pyqt_custom_titlebar_window/__init__.py
pyqt_custom_titlebar_window/button.py
pyqt_custom_titlebar_window/button_style_helper.py
pyqt_custom_titlebar_window/customTitlebarWindow.py
pyqt_custom_titlebar_window/macButtonsWidget.py
pyqt_custom_titlebar_window/svgIconTextWidget.py
pyqt_custom_titlebar_window/svgLabel.py
pyqt_custom_titlebar_window/titlebarButtonsWidget.py
pyqt_custom_titlebar_window/topTitleBarWidget.py
pyqt_custom_titlebar_window/windowsButtonsWidget.py
pyqt_custom_titlebar_window/ico/__init__.py
pyqt_custom_titlebar_window/ico/fold.svg
pyqt_custom_titlebar_window/ico/full_screen.svg
pyqt_custom_titlebar_window/ico/help.svg
pyqt_custom_titlebar_window/ico/search.svg
pyqt_custom_titlebar_window/ico/tack.svg
pyqt_custom_titlebar_window/ico/unfold.svg
pyqt_custom_titlebar_window-0.1.0.dist-info/LICENSE
pyqt_custom_titlebar_window-0.1.0.dist-info/METADATA
pyqt_custom_titlebar_window-0.1.0.dist-info/WHEEL
pyqt_custom_titlebar_window-0.1.0.dist-info/top_level.txt
pyqt_custom_titlebar_window-0.1.0.dist-info/RECORD
