Metadata-Version: 2.1
Name: pyqt-custom-titlebar-window
Version: 0.1.0
Summary: PyQt custom titlebar window (resizable, movable, minimize/maximize/close, etc.)
Home-page: https://github.com/yjg30737/pyqt-custom-titlebar-window.git
Author: Jung Gyu Yoon
Author-email: yjg30737@gmail.com
License: MIT
License-File: LICENSE
Requires-Dist: PyQt5 >=5.15
Requires-Dist: pyqt-frameless-window ==0.0.61
